{
  "name": "size5/prog939.json",
  "program": "(root (DROP (MAP-DIV (ZIPWITH-MIN (SCANL1-PLUS input0) (SCANL1-MIN input0)) 2) input1))",
  "examples": [
    {
      "input": [
        [
          36,
          46,
          -45,
          -30,
          45,
          -78,
          39,
          -64,
          84,
          -94,
          49,
          118,
          -49,
          -98,
          25,
          33,
          -39,
          -13,
          117,
          99
        ],
        7
      ],
      "output": [
        -39,
        -39,
        -47,
        -47,
        -47,
        -47,
        -49,
        -49,
        -49,
        -49,
        -49,
        -49,
        -49
      ]
    },
    {
      "input": [
        [
          -49,
          4,
          -78,
          -33,
          -25,
          2,
          -66,
          -57,
          -16,
          -18,
          87,
          89,
          40,
          -98,
          -109,
          -23,
          49,
          74,
          -38,
          122
        ],
        15
      ],
      "output": [
        -175,
        -150,
        -113,
        -132,
        -71
      ]
    },
    {
      "input": [
        [
          -31,
          53,
          28,
          -126,
          -22,
          -14,
          -127,
          39,
          101,
          -16,
          -77,
          -75,
          -98,
          -12,
          84,
          43,
          55,
          79,
          -29,
          -60
        ],
        8
      ],
      "output": [
        -63,
        -63,
        -96,
        -133,
        -182,
        -188,
        -146,
        -125,
        -97,
        -63,
        -72,
        -102
      ]
    },
    {
      "input": [
        [
          -69,
          126,
          -8,
          70,
          119,
          -104,
          -118,
          15,
          -51,
          40,
          69,
          117,
          -20,
          80,
          24,
          -105,
          23,
          36,
          31,
          66
        ],
        5
      ],
      "output": [
        -52,
        -59,
        -59,
        -59,
        -59,
        -59,
        -59,
        -59,
        -59,
        -59,
        -59,
        -59,
        -59,
        -59,
        -59
      ]
    },
    {
      "input": [
        [
          112,
          31,
          30,
          -11,
          -9,
          37,
          -95,
          -120,
          -29,
          112,
          48,
          -79,
          -104,
          -81,
          -97,
          84,
          39,
          30,
          -59,
          72
        ],
        11
      ],
      "output": [
        -60,
        -60,
        -79,
        -127,
        -85,
        -66,
        -60,
        -80,
        -60
      ]
    }
  ]
}