{
  "name": "size5/prog593.json",
  "program": "(root (DROP (MAP-MUL (MAP-PLUS (FILTER input0 l(a,b).(!= a b) -3) 2) 2) (HEAD input0)))",
  "examples": [
    {
      "input": [
        [
          17,
          60,
          -93,
          -35,
          -120,
          119,
          -127,
          -46,
          -58,
          94,
          124,
          7,
          118,
          77,
          -20,
          30,
          -120,
          -44,
          -126,
          0
        ]
      ],
      "output": [
        -84,
        -248,
        4
      ]
    },
    {
      "input": [
        [
          18,
          102,
          -34,
          -26,
          82,
          39,
          -15,
          -86,
          74,
          -79,
          9,
          100,
          -106,
          53,
          125,
          -126,
          38,
          -105,
          -48,
          117
        ]
      ],
      "output": [
        -92,
        238
      ]
    },
    {
      "input": [
        [
          5,
          -44,
          -105,
          99,
          34,
          -53,
          -53,
          -4,
          -75,
          29,
          103,
          109,
          -112,
          -26,
          -76,
          -106,
          112,
          -90,
          15,
          71
        ]
      ],
      "output": [
        -102,
        -102,
        -4,
        -146,
        62,
        210,
        222,
        -220,
        -48,
        -148,
        -208,
        228,
        -176,
        34,
        146
      ]
    },
    {
      "input": [
        [
          13,
          -66,
          99,
          115,
          -78,
          95,
          54,
          -12,
          -41,
          -114,
          40,
          107,
          -102,
          -83,
          52,
          -127,
          56,
          -45,
          -91,
          85
        ]
      ],
      "output": [
        -162,
        108,
        -250,
        116,
        -86,
        -178,
        174
      ]
    },
    {
      "input": [
        [
          9,
          127,
          69,
          -54,
          -112,
          57,
          41,
          9,
          -63,
          -18,
          -28,
          22,
          102,
          -32,
          -36,
          -67,
          -69,
          108,
          63,
          63
        ]
      ],
      "output": [
        -32,
        -52,
        48,
        208,
        -60,
        -68,
        -130,
        -134,
        220,
        130,
        130
      ]
    }
  ]
}