{
  "name": "size5/prog674.json",
  "program": "(root (ACCESS (MAP-MUL input0 3) (HEAD (REVERSE (SCANL1-MINUS input0)))))",
  "examples": [
    {
      "input": [
        [
          60,
          -61,
          67,
          47,
          -72,
          -59,
          -74,
          -119,
          67,
          61,
          103,
          89,
          64,
          -58,
          3,
          3,
          -38,
          103,
          -105,
          39
        ]
      ],
      "output": 180
    },
    {
      "input": [
        [
          106,
          -70,
          -25,
          10,
          -36,
          -20,
          -22,
          -37,
          77,
          104,
          -4,
          75,
          -103,
          15,
          123,
          -119,
          80,
          -66,
          0,
          120
        ]
      ],
      "output": -108
    },
    {
      "input": [
        [
          123,
          -99,
          68,
          70,
          -32,
          -58,
          119,
          73,
          10,
          -105,
          -57,
          110,
          -65,
          27,
          -26,
          -77,
          116,
          -66,
          -13,
          114
        ]
      ],
      "output": -78
    },
    {
      "input": [
        [
          -79,
          -112,
          -95,
          -107,
          20,
          51,
          15,
          -7,
          -76,
          87,
          -46,
          -42,
          23,
          0,
          -57,
          -100,
          99,
          109,
          106,
          39
        ]
      ],
      "output": -171
    },
    {
      "input": [
        [
          -69,
          82,
          119,
          -32,
          -62,
          -15,
          40,
          10,
          -71,
          11,
          70,
          -124,
          113,
          -120,
          -64,
          -68,
          84,
          -59,
          62,
          -60
        ]
      ],
      "output": -204
    }
  ]
}