{
  "name": "size5/prog499.json",
  "program": "(root (MAXIMUM (MAP-PLUS (MAP-PLUS (SCANL1-MUL (SCANL1-MUL input0)) 1) 2)))",
  "examples": [
    {
      "input": [
        [
          -63,
          -92,
          84,
          -66,
          35,
          -48,
          -109,
          77,
          -85,
          -9,
          37,
          100,
          -63,
          -121,
          -76,
          107,
          -88,
          -5,
          36,
          -1
        ]
      ],
      "output": 3
    },
    {
      "input": [
        [
          61,
          -27,
          -54,
          -16,
          -107,
          -7,
          17,
          120,
          92,
          -103,
          102,
          51,
          -35,
          -104,
          -85,
          41,
          -29,
          -50,
          -77,
          -100
        ]
      ],
      "output": 64
    },
    {
      "input": [
        [
          102,
          -96,
          121,
          -99,
          120,
          80,
          -81,
          -100,
          69,
          -51,
          -43,
          37,
          -92,
          -49,
          -39,
          95,
          -20,
          -26,
          -77,
          44
        ]
      ],
      "output": 105
    },
    {
      "input": [
        [
          94,
          -68,
          39,
          79,
          -56,
          -116,
          -51,
          24,
          -44,
          6,
          92,
          43,
          97,
          -106,
          3,
          53,
          125,
          60,
          -79,
          81
        ]
      ],
      "output": 97
    },
    {
      "input": [
        [
          12,
          -47,
          -98,
          -48,
          123,
          -72,
          -43,
          -4,
          -45,
          42,
          -17,
          100,
          24,
          -10,
          6,
          78,
          -13,
          -90,
          107,
          45
        ]
      ],
      "output": 15
    }
  ]
}