{
  "name": "prog29.json",
  "program": "(root [id=1](TAKE [id=2](SCANL1-MAX [id=245](MAP-PLUS [id=326](SORT [id=353]input0) [id=327]3)) [id=3](LAST [id=125]input0)))",
  "examples": [
    {
      "input": [
        [
          -86,
          118,
          105,
          -27,
          43,
          13,
          103,
          64,
          -120,
          -119,
          -20,
          29,
          48,
          -14,
          -50,
          63,
          77,
          -3,
          -91,
          2
        ]
      ],
      "output": [
        -117,
        -116
      ]
    },
    {
      "input": [
        [
          88,
          -26,
          118,
          36,
          65,
          123,
          -119,
          104,
          -88,
          125,
          37,
          -103,
          21,
          -2,
          -65,
          -21,
          29,
          66,
          123,
          3
        ]
      ],
      "output": [
        -116,
        -100,
        -85
      ]
    },
    {
      "input": [
        [
          -107,
          60,
          82,
          106,
          -106,
          -71,
          -25,
          -112,
          -62,
          107,
          2,
          73,
          -94,
          -68,
          23,
          -39,
          112,
          117,
          105,
          4
        ]
      ],
      "output": [
        -109,
        -104,
        -103,
        -91
      ]
    },
    {
      "input": [
        [
          55,
          -89,
          87,
          -128,
          -52,
          102,
          -16,
          -83,
          -10,
          -107,
          -46,
          -47,
          -72,
          8,
          33,
          -65,
          -95,
          -23,
          -126,
          3
        ]
      ],
      "output": [
        -125,
        -123,
        -104
      ]
    },
    {
      "input": [
        [
          -73,
          24,
          57,
          18,
          -21,
          11,
          -66,
          -3,
          20,
          -49,
          -86,
          -44,
          -39,
          26,
          69,
          -100,
          25,
          48,
          -69,
          5
        ]
      ],
      "output": [
        -97,
        -83,
        -70,
        -66,
        -63
      ]
    }
  ]
}
